QtDesign/QtdUiTools.py
QtDesign/QtdWidgets.py
QtDesign/__init__.py
QtDesign-0.1.0.dist-info/LICENSE
QtDesign-0.1.0.dist-info/METADATA
QtDesign-0.1.0.dist-info/WHEEL
QtDesign-0.1.0.dist-info/top_level.txt
QtDesign-0.1.0.dist-info/RECORD
