Metadata-Version: 2.1
Name: QtDesign
Version: 0.1.0
Summary: Custom widgets and utilities for PySide2
Home-page: https://github.com/JevexEndo/qtdesign
Author: Jevex
Author-email: jevex.endo@gmail.com
License: UNKNOWN
Project-URL: Bug Tracker, https://github.com/JevexEndo/qtdesign/issues
Platform: UNKNOWN
Classifier: Programming Language :: Python :: 3
Classifier: License :: OSI Approved :: MIT License
Classifier: Operating System :: OS Independent
Requires-Python: >=3.7
License-File: LICENSE
